splink_comparison_viewer/__init__.py
splink_comparison_viewer/css/custom.css
splink_comparison_viewer/get_data.py
splink_comparison_viewer/jinja/template.j2
splink_comparison_viewer/js_lib/splink_vis_utils.js
splink_comparison_viewer/js_lib/vega-embed@6
splink_comparison_viewer/js_lib/vega-lite@5
splink_comparison_viewer/js_lib/vega@5
splink_comparison_viewer/render_template.py
splink_comparison_viewer-0.1.4.dist-info/LICENSE
splink_comparison_viewer-0.1.4.dist-info/WHEEL
splink_comparison_viewer-0.1.4.dist-info/METADATA
splink_comparison_viewer-0.1.4.dist-info/RECORD
