Metadata-Version: 2.1
Name: splink-comparison-viewer
Version: 0.1.4
Summary: Create an interactive webpage to visualise Splink record comparisons
Author: Robin Linacre
Author-email: robinlinacre@hotmail.com
Requires-Python: >=3.6,<4.0
Classifier: Programming Language :: Python :: 3
Classifier: Programming Language :: Python :: 3.6
Classifier: Programming Language :: Python :: 3.7
Classifier: Programming Language :: Python :: 3.8
Classifier: Programming Language :: Python :: 3.9
Requires-Dist: Jinja2 (>=3.0.2,<4.0.0)
